pincercli/__init__.py
pincercli-0.0.0.dist-info/METADATA
pincercli-0.0.0.dist-info/WHEEL
pincercli-0.0.0.dist-info/entry_points.txt
pincercli-0.0.0.dist-info/top_level.txt
pincercli-0.0.0.dist-info/RECORD
