Metadata-Version: 2.1
Name: pincercli
Version: 0.0.0
Summary: A command line interface to bring automation to your pincer projects.
Home-page: https://pincer.dev
Author: Pincer-org
Author-email: contact@pincer.dev
License: MIT
Platform: unix
Platform: linux
Platform: osx
Platform: cygwin
Platform: windows
Classifier: Development Status :: 2 - Pre-Alpha
Classifier: Intended Audience :: Developers
Classifier: Topic :: Software Development :: Build Tools
Classifier: License :: OSI Approved :: MIT License
Classifier: Programming Language :: Python :: 3 :: Only
Classifier: Programming Language :: Python :: 3.8
Classifier: Programming Language :: Python :: 3.9
Requires-Python: >=3.8
